<?xml version="1.0" encoding="utf-8"?>
<List xmlns:ows="Microsoft SharePoint" Title="MonthlyReportList" FolderCreation="FALSE" Direction="$Resources:Direction;" Url="Lists/SharePointDelegations-MonthlyReportList" BaseType="0" xmlns="http://schemas.microsoft.com/sharepoint/">
  <MetaData>
    <ContentTypes>
      <ContentTypeRef ID="0x010084534150162D41F2957E6D795FB00A5E"/>
    </ContentTypes>
    <Fields>
      <Field ID="{eedeb061-2368-4981-bce4-8cacb8bd865d}" Name="MonthIndicator" DisplayName="Month" Type="DateTime" Group="LS Columns" Format="DateOnly">
      </Field>
      <Field ID="{8fb3d31e-ccdb-4b8d-a280-ed3e632983bd}" Name="MonthlyCost" DisplayName="Monthly Cost" Type="Currency" LCID="1045" Group="LS Columns">
      </Field>
    </Fields>
    <Views>
      <View BaseViewID="0" Type="HTML" MobileView="TRUE" TabularView="FALSE">
        <Toolbar Type="Standard" />
        <XslLink Default="TRUE">main.xsl</XslLink>
        <RowLimit Paged="TRUE">30</RowLimit>
        <ViewFields>
          <FieldRef Name="LinkTitleNoMenu">
          </FieldRef>
        </ViewFields>
        <Query>
          <OrderBy>
            <FieldRef Name="Modified" Ascending="FALSE">
            </FieldRef>
          </OrderBy>
        </Query>
        <ParameterBindings>
          <ParameterBinding Name="AddNewAnnouncement" Location="Resource(wss,addnewitem)" />
          <ParameterBinding Name="NoAnnouncements" Location="Resource(wss,noXinviewofY_LIST)" />
          <ParameterBinding Name="NoAnnouncementsHowTo" Location="Resource(wss,noXinviewofY_ONET_HOME)" />
        </ParameterBindings>
      </View>
      <View BaseViewID="1" Type="HTML" WebPartZoneID="Main" DisplayName="$Resources:core,objectiv_schema_mwsidcamlidC24;" DefaultView="TRUE" MobileView="TRUE" MobileDefaultView="TRUE" SetupPath="pages\viewpage.aspx" ImageUrl="/_layouts/images/generic.png" Url="AllItems.aspx">
        <Toolbar Type="Standard" />
        <XslLink Default="TRUE">main.xsl</XslLink>
        <RowLimit Paged="TRUE">30</RowLimit>
        <ViewFields>
          <FieldRef Name="Attachments">
          </FieldRef>
          <FieldRef ID="{EEDEB061-2368-4981-BCE4-8CACB8BD865D}" Name="MonthIndicator" />
          <FieldRef ID="{8FB3D31E-CCDB-4B8D-A280-ED3E632983BD}" Name="MonthlyCost" />
        </ViewFields>
        <Query>
          <OrderBy>
            <FieldRef Name="ID">
            </FieldRef>
          </OrderBy>
        </Query>
        <ParameterBindings>
          <ParameterBinding Name="NoAnnouncements" Location="Resource(wss,noXinviewofY_LIST)" />
          <ParameterBinding Name="NoAnnouncementsHowTo" Location="Resource(wss,noXinviewofY_DEFAULT)" />
        </ParameterBindings>
      </View>
    </Views>
    <Forms>
      <Form Type="DisplayForm" Url="DispForm.aspx" SetupPath="pages\form.aspx" WebPartZoneID="Main" />
      <Form Type="EditForm" Url="EditForm.aspx" SetupPath="pages\form.aspx" WebPartZoneID="Main" />
      <Form Type="NewForm" Url="NewForm.aspx" SetupPath="pages\form.aspx" WebPartZoneID="Main" />
    </Forms>
  </MetaData>
</List>